{"events":[{"type":"show","id":"26:127","name":"Consider an input string, e.g. abaccbab ∈ Σ*","index":1,"disabled":false},{"type":"show","id":"93:12","name":"Group 13","index":5,"disabled":false},{"type":"show","id":"26:174","name":"Next, the machine keeps on updating its configuration, until:","index":2,"disabled":false},{"type":"show","id":"26:176","name":"– an accept transition is used","index":3,"disabled":false},{"type":"show","id":"93:17","name":"– a reject transition is used, or the head falls off the tape","index":4,"disabled":false},{"type":"show","id":"93:15","name":"– the run goes on forever, avoiding accept and reject","index":6,"disabled":false}],"name":"Turing machine semantics","id":"26:118"}